PolibasePersonReviewNotificationService/__init__.py
PolibasePersonReviewNotificationService/__main__.py
PolibasePersonReviewNotificationService/api.py
PolibasePersonReviewNotificationService/const.py
PolibasePersonReviewNotificationService/service.py
WSService/__init__.py
WSService/__main__.py
WSService/const.py
WSService/service.py
pih_plb_rw_ntf-1.0.dist-info/METADATA
pih_plb_rw_ntf-1.0.dist-info/WHEEL
pih_plb_rw_ntf-1.0.dist-info/entry_points.txt
pih_plb_rw_ntf-1.0.dist-info/top_level.txt
pih_plb_rw_ntf-1.0.dist-info/RECORD
