Metadata-Version: 2.1
Name: pih-plb-rw-ntf
Version: 1.0
Summary: PIH Polibase Person Review Notification service module
Home-page: https://pacifichosp.com/
Author: Nikita Karachentsev
Author-email: it@pacifichosp.com
License: MIT
Requires-Dist: ipih
